external_site_parser/Action.py
external_site_parser/Analysis.py
external_site_parser/Baseline.py
external_site_parser/Fixlet.py
external_site_parser/Task.py
external_site_parser/__init__.py
external_site_parser/utils.py
external_site_parser-0.4.8.dist-info/LICENSE
external_site_parser-0.4.8.dist-info/METADATA
external_site_parser-0.4.8.dist-info/WHEEL
external_site_parser-0.4.8.dist-info/top_level.txt
external_site_parser-0.4.8.dist-info/RECORD
